sentry_jsonish/__init__.py
sentry_jsonish/py.typed
sentry_jsonish/test_jsonish.py
sentry_jsonish-0.0.2.dist-info/METADATA
sentry_jsonish-0.0.2.dist-info/WHEEL
sentry_jsonish-0.0.2.dist-info/top_level.txt
sentry_jsonish-0.0.2.dist-info/RECORD
