Metadata-Version: 2.1
Name: sentry-jsonish
Version: 0.0.2
Summary: Sentry wrapper to the go-jsonnet library
Classifier: Programming Language :: Python :: 3
Classifier: Operating System :: OS Independent
Requires-Python: >=3.8
